aang/__init__.py
aang/aang.py
aang-0.0.3.dist-info/METADATA
aang-0.0.3.dist-info/WHEEL
aang-0.0.3.dist-info/top_level.txt
aang-0.0.3.dist-info/RECORD
