Metadata-Version: 2.1
Name: aang
Version: 0.0.3
Summary: A mildly malicious library to contantly set the user's background to AANG
Home-page: UNKNOWN
Author: Abhinav G
Author-email: agupta.cam7@gmail.com
License: MIT
Keywords: aang,python,background,image,png,wav,set background,windows
Platform: UNKNOWN
Classifier: Programming Language :: Python :: 3
Classifier: License :: OSI Approved :: MIT License
Classifier: Operating System :: OS Independent
